poetry_scmver/__init__.py
poetry_scmver/version.py
zzz_poetry_scmver.pth
poetry_scmver-0.1.2.dev6.dist-info/LICENSE.txt
poetry_scmver-0.1.2.dev6.dist-info/WHEEL
poetry_scmver-0.1.2.dev6.dist-info/METADATA
poetry_scmver-0.1.2.dev6.dist-info/RECORD
