Metadata-Version: 2.1
Name: poetry-scmver
Version: 0.1.2.dev6
Summary: Plugin for Poetry to enable dynamic versioning based on VCS tags for semver
License: MIT
Keywords: poetry,scm,version,plugin
Author: Lorenzo A. Garcia Calzadilla
Author-email: lorenzogarciacalzadilla@gmail.com
Requires-Python: >=3.7,<4.0
Classifier: Development Status :: 4 - Beta
Classifier: Environment :: Plugins
Classifier: Intended Audience :: Developers
Classifier: License :: OSI Approved :: MIT License
Classifier: Natural Language :: English
Classifier: Operating System :: OS Independent
Classifier: Programming Language :: Python :: 3
Classifier: Programming Language :: Python :: 3.7
Classifier: Topic :: Software Development :: Build Tools
Classifier: Topic :: Software Development :: Libraries :: Python Modules
Classifier: Topic :: Software Development :: Version Control
Classifier: Topic :: System :: Software Distribution
Classifier: Topic :: Utilities
Requires-Dist: poetry
Requires-Dist: scmver
Requires-Dist: tomlkit
